{
    "track": {
        "level": {
            "level1": [
                "Key",
                "Title",
                "Summary",
                "Duration",
                "Added"
            ],
            "level2": [
                "Key",
                "Title",
                "Summary",
                "Duration",
                "Added",
                "Part File",
                "Part File Combined",
                "Part File Path"
            ],
            "all": [
                "Added",
                "Art url",
                "Duration",
                "Key",
                "Media Audio Channels",
                "Media Audio Codec",
                "Media Bitrate",
                "Media Container",
                "Part Container",
                "Part Deep Analysis Version",
                "Part Duration",
                "Part File",
                "Part File Combined",
                "Part File Path",
                "Part Required Bandwidths",
                "Part Size",
                "Part Size as Bytes",
                "Poster url",
                "Summary",
                "Title",
                "Updated"
            ]
        }
    }
}