{
    "artist": {
        "level": {
            "level1": [
                "Key",
                "Title",
                "Sort title",
                "Summary"
            ],
            "level2": [
                "Key",
                "Title",
                "Sort title",
                "Summary",
                "Poster url",
                "Added",
                "Updated",
                "Genre"
            ],
            "all": [
                "Added",
                "Art url",
                "Country",
                "Genre",
                "Key",
                "Last Viewed at",
                "Mood",
                "Poster url",
                "Sort title",
                "Style",
                "Summary",
                "Title",
                "Updated"
            ]
        }
    }
}